exodus_bundler/__init__.py
exodus_bundler/bundling.py
exodus_bundler/cli.py
exodus_bundler/dependency_detection.py
exodus_bundler/errors.py
exodus_bundler/input_parsing.py
exodus_bundler/launchers.py
exodus_bundler/templating.py
exodus_bundler/templates/install-bundle-noninteractive.sh
exodus_bundler/templates/install-bundle.sh
exodus_bundler/templates/launcher.c
exodus_bundler/templates/launcher.sh
exodus_bundler-2.0.4.dist-info/LICENSE.md
exodus_bundler-2.0.4.dist-info/METADATA
exodus_bundler-2.0.4.dist-info/WHEEL
exodus_bundler-2.0.4.dist-info/entry_points.txt
exodus_bundler-2.0.4.dist-info/top_level.txt
exodus_bundler-2.0.4.dist-info/RECORD
